[
  {
    "name": "Spaghetti Bolognese",
    "ingredients": [
      "spaghetti",
      "ground beef",
      "tomato sauce",
      "onions",
      "garlic"
    ]
  },
  {
    "name": "Vegetarian Stir Fry",
    "ingredients": [
      "tofu",
      "broccoli",
      "carrots",
      "soy sauce",
      "ginger"
    ]
  },
  {
    "name": "Napoli",
    "ingredients": [
      "Spaghetti",
      "pomodoro",
      "parmesan"
    ]
  },
  {
    "name": "Napoli",
    "ingredients": [
      "Spaghetti",
      "pomodoro",
      "parmesan"
    ]
  }
]